jsdesign_mcp/__init__.py
jsdesign_mcp/server.py
jsdesign_mcp-0.0.3.dist-info/licenses/LICENSE
jsdesign_mcp-0.0.3.dist-info/METADATA
jsdesign_mcp-0.0.3.dist-info/WHEEL
jsdesign_mcp-0.0.3.dist-info/entry_points.txt
jsdesign_mcp-0.0.3.dist-info/top_level.txt
jsdesign_mcp-0.0.3.dist-info/RECORD
